MANIFEST.in
README.md
setup.py
appscale/__init__.py
appscale/tools/__init__.py
appscale/tools/appcontroller_client.py
appscale/tools/appengine_helper.py
appscale/tools/appscale.py
appscale/tools/appscale_logger.py
appscale/tools/appscale_stats.py
appscale/tools/appscale_tools.py
appscale/tools/cluster_stats.py
appscale/tools/custom_exceptions.py
appscale/tools/local_state.py
appscale/tools/node_layout.py
appscale/tools/parse_args.py
appscale/tools/registration_helper.py
appscale/tools/remote_helper.py
appscale/tools/utils.py
appscale/tools/version_helper.py
appscale/tools/admin_api/__init__.py
appscale/tools/admin_api/client.py
appscale/tools/admin_api/handler.py
appscale/tools/admin_api/version.py
appscale/tools/scripts/__init__.py
appscale/tools/scripts/add_instances.py
appscale/tools/scripts/add_keypair.py
appscale/tools/scripts/appscale.py
appscale/tools/scripts/describe_instances.py
appscale/tools/scripts/gather_logs.py
appscale/tools/scripts/get_property.py
appscale/tools/scripts/relocate_app.py
appscale/tools/scripts/remove_app.py
appscale/tools/scripts/reset_pwd.py
appscale/tools/scripts/run_instances.py
appscale/tools/scripts/services.py
appscale/tools/scripts/set_property.py
appscale/tools/scripts/show_stats.py
appscale/tools/scripts/terminate_instances.py
appscale/tools/scripts/upload_app.py
appscale/tools/templates/AppScalefile
appscale/tools/templates/ips.yaml
appscale/tools/templates/sshcopyid
appscale_tools.egg-info/PKG-INFO
appscale_tools.egg-info/SOURCES.txt
appscale_tools.egg-info/dependency_links.txt
appscale_tools.egg-info/entry_points.txt
appscale_tools.egg-info/namespace_packages.txt
appscale_tools.egg-info/requires.txt
appscale_tools.egg-info/top_level.txt
test/test_appcontroller_client.py
test/test_appengine_helper.py
test/test_appscale.py
test/test_appscale_add_instances.py
test/test_appscale_add_keypair.py
test/test_appscale_describe_instances.py
test/test_appscale_gather_logs.py
test/test_appscale_get_property.py
test/test_appscale_logger.py
test/test_appscale_register.py
test/test_appscale_relocate_app.py
test/test_appscale_remove_app.py
test/test_appscale_reset_pwd.py
test/test_appscale_run_instances.py
test/test_appscale_set_property.py
test/test_appscale_terminate_instances.py
