Metadata-Version: 2.1
Name: appscale-tools
Version: 3.8.0
Summary: A set of command-line tools for interacting with AppScale
Home-page: https://github.com/AppScale/appscale-tools
Author: AppScale Systems, Inc.
License: Apache License 2.0
Keywords: appscale google-app-engine python java go php
Platform: Posix; MacOS X
Classifier: Development Status :: 5 - Production/Stable
Classifier: Environment :: Console
Classifier: Intended Audience :: Developers
Classifier: Intended Audience :: System Administrators
Classifier: License :: OSI Approved :: Apache Software License
Classifier: Programming Language :: Python :: 2.7
Classifier: Topic :: Utilities
Provides-Extra: testing
